{
  "type": "騷話文案",
  "updated": "2026-05-20T20:56:05.380Z",
  "updateTime": "2026/5/21 上午4:56:05",
  "totalCount": 50,
  "targetCount": 50,
  "completionRate": "100.0%",
  "convertedToTraditional": true,
  "copywritings": [
    {
      "id": 1,
      "content": "要做愛，不要作戰 ",
      "length": 9,
      "addedAt": "2026-05-20T20:56:05.380Z"
    },
    {
      "id": 2,
      "content": "拔屌無情。 --莫言《檀香刑》 ",
      "length": 16,
      "addedAt": "2026-05-20T20:56:05.380Z"
    },
    {
      "id": 3,
      "content": "屌到用時方恨短",
      "length": 7,
      "addedAt": "2026-05-20T20:56:05.380Z"
    },
    {
      "id": 4,
      "content": "不知死活的瘋女人 ",
      "length": 9,
      "addedAt": "2026-05-20T20:56:05.380Z"
    },
    {
      "id": 5,
      "content": "用我三生煙火，換你一生迷離。為你塵埃落定，傾覆一世繁華。 ",
      "length": 29,
      "addedAt": "2026-05-20T20:56:05.380Z"
    },
    {
      "id": 6,
      "content": "我有一個問題，那就是到底要講多少情話，才能把你灌醉啊，到底要用什麼辦法撩撥，才能讓你動心。簡單點來說，我想和你睡覺。 ",
      "length": 59,
      "addedAt": "2026-05-20T20:56:05.380Z"
    },
    {
      "id": 7,
      "content": "姐最強大的事情，就是不靠菸酒，也能流氓並文藝著。",
      "length": 24,
      "addedAt": "2026-05-20T20:56:05.380Z"
    },
    {
      "id": 8,
      "content": "見到別人時 我有206塊骨頭 見到你時 我有207塊",
      "length": 26,
      "addedAt": "2026-05-20T20:56:05.380Z"
    },
    {
      "id": 9,
      "content": "“你心不心疼我啊？”“心在你那裡，疼不疼你說了算。” ",
      "length": 27,
      "addedAt": "2026-05-20T20:56:05.380Z"
    },
    {
      "id": 10,
      "content": "春風十里 五十里 一百里 體測八百米 海底兩萬裡 德芙巧克力 香草味八喜 可可布朗尼 榴蓮菠蘿蜜 芝士玉米粒 雞汁土豆泥 黑椒牛裡脊 黃燜辣子雞 紅燒排骨醬醋魚 不如你 全都不如你 ",
      "length": 91,
      "addedAt": "2026-05-20T20:56:05.380Z"
    },
    {
      "id": 11,
      "content": "別人我不知道，反正我要喜歡一個姑娘我就想操翻她 ",
      "length": 24,
      "addedAt": "2026-05-20T20:56:05.380Z"
    },
    {
      "id": 12,
      "content": "想睡你的那種喜歡，以天天可以和你上床為目的的那種追求，我說的夠明確了嗎？ ",
      "length": 37,
      "addedAt": "2026-05-20T20:56:05.380Z"
    },
    {
      "id": 13,
      "content": "“你想什麼時候結婚？”“不知道啊”“嗯，那好吧，等你想好了我再娶你吧” ",
      "length": 36,
      "addedAt": "2026-05-20T20:56:05.380Z"
    },
    {
      "id": 14,
      "content": "“你想什麼時候結婚？”“不知道啊”“嗯，那好吧，等你想好了我再娶你吧”",
      "length": 35,
      "addedAt": "2026-05-20T20:56:05.380Z"
    },
    {
      "id": 15,
      "content": "幸福其實好簡單 我餵奶給你喝 你下面給我吃",
      "length": 21,
      "addedAt": "2026-05-20T20:56:05.380Z"
    },
    {
      "id": 16,
      "content": "我也曾倒掛在你的身上 ",
      "length": 11,
      "addedAt": "2026-05-20T20:56:05.380Z"
    },
    {
      "id": 17,
      "content": "“我要偷你的體溫” “說人話” “要抱抱” ",
      "length": 22,
      "addedAt": "2026-05-20T20:56:05.380Z"
    },
    {
      "id": 18,
      "content": "我進入你身體的時候 就像溫帶海洋性氣候 一直都是暖暖的 ",
      "length": 28,
      "addedAt": "2026-05-20T20:56:05.380Z"
    },
    {
      "id": 19,
      "content": "都喜歡乾淨的女人 卻又喜歡把她弄髒 ",
      "length": 18,
      "addedAt": "2026-05-20T20:56:05.380Z"
    },
    {
      "id": 20,
      "content": "別調戲我，不然我非禮你 ",
      "length": 12,
      "addedAt": "2026-05-20T20:56:05.380Z"
    },
    {
      "id": 21,
      "content": "浪蕩一生 鍾情一人 微風十里 只想要你。",
      "length": 20,
      "addedAt": "2026-05-20T20:56:05.380Z"
    },
    {
      "id": 22,
      "content": "你知道什麼酒最好喝嗎 天長地久",
      "length": 15,
      "addedAt": "2026-05-20T20:56:05.380Z"
    },
    {
      "id": 23,
      "content": "和她在一起感覺自己就是一個振動棒 ",
      "length": 17,
      "addedAt": "2026-05-20T20:56:05.380Z"
    },
    {
      "id": 24,
      "content": "想把你拖出去糟蹋了 ",
      "length": 10,
      "addedAt": "2026-05-20T20:56:05.380Z"
    },
    {
      "id": 25,
      "content": "女人，就像馬路一樣，越是凹凸不平，越是危險 ",
      "length": 22,
      "addedAt": "2026-05-20T20:56:05.380Z"
    },
    {
      "id": 26,
      "content": "老師說，同學們，不要早戀，你們現在談的，以後都是別人的老婆，我一聽，臥槽，別人的老婆，想想就刺激。",
      "length": 49,
      "addedAt": "2026-05-20T20:56:05.380Z"
    },
    {
      "id": 27,
      "content": "“你挑食麼？”“不挑”“那你怎麼還不把我吃掉” ",
      "length": 24,
      "addedAt": "2026-05-20T20:56:05.380Z"
    },
    {
      "id": 28,
      "content": "見到我的時候 記得第一時間吻我",
      "length": 15,
      "addedAt": "2026-05-20T20:56:05.380Z"
    },
    {
      "id": 29,
      "content": "女朋友長得非常漂亮是怎樣一種體驗？......都不捨得關燈 ",
      "length": 30,
      "addedAt": "2026-05-20T20:56:05.380Z"
    },
    {
      "id": 30,
      "content": "今晚能採蘑菇嗎？ ",
      "length": 9,
      "addedAt": "2026-05-20T20:56:05.380Z"
    },
    {
      "id": 31,
      "content": "\"晚上睡不著覺就開始數羊：一隻羊、兩隻羊、三隻羊、四隻羊、喜羊羊，美羊羊，懶羊羊，沸羊羊，小肥羊，海底撈，麻醬，小料，金針菇，蝦滑，寬粉，海帶，豆芽，大海螺，茼蒿，菠菜……乾啤，淡爽，老雪花，……媽了個逼的，不睡了，下樓！\"",
      "length": 112,
      "addedAt": "2026-05-20T20:56:05.380Z"
    },
    {
      "id": 32,
      "content": "你的淫蕩超乎我想象 ",
      "length": 10,
      "addedAt": "2026-05-20T20:56:05.380Z"
    },
    {
      "id": 33,
      "content": "不思進取...思你",
      "length": 9,
      "addedAt": "2026-05-20T20:56:05.380Z"
    },
    {
      "id": 34,
      "content": "你哦哦額額恩恩的回覆 搞得我好像在上你一樣",
      "length": 21,
      "addedAt": "2026-05-20T20:56:05.380Z"
    },
    {
      "id": 35,
      "content": "A:你可以做我的奧利奧嗎？ B:什麼意思 A：我想泡你啊 ",
      "length": 29,
      "addedAt": "2026-05-20T20:56:05.380Z"
    },
    {
      "id": 36,
      "content": "等我找到你我一定把我這麼多年攢的炮都給你補上",
      "length": 22,
      "addedAt": "2026-05-20T20:56:05.380Z"
    },
    {
      "id": 37,
      "content": "什麼是陪伴？ 不讓一個人，一個人 ",
      "length": 17,
      "addedAt": "2026-05-20T20:56:05.380Z"
    },
    {
      "id": 38,
      "content": "老妹得勁不，坐上來自己動麻溜滴 ",
      "length": 16,
      "addedAt": "2026-05-20T20:56:05.380Z"
    },
    {
      "id": 39,
      "content": "我想吸你脖子，給你種草莓 想在沙發裡跟你縮成一團",
      "length": 24,
      "addedAt": "2026-05-20T20:56:05.380Z"
    },
    {
      "id": 40,
      "content": "本宮宣告以後廢除丁丁 有你的口接替 ",
      "length": 18,
      "addedAt": "2026-05-20T20:56:05.380Z"
    },
    {
      "id": 41,
      "content": "我的胸就是讓我閨蜜一手帶大的 ",
      "length": 15,
      "addedAt": "2026-05-20T20:56:05.380Z"
    },
    {
      "id": 42,
      "content": "願得一人心 免得老相親",
      "length": 11,
      "addedAt": "2026-05-20T20:56:05.380Z"
    },
    {
      "id": 43,
      "content": "我對象很好，為什麼象不理我",
      "length": 13,
      "addedAt": "2026-05-20T20:56:05.380Z"
    },
    {
      "id": 44,
      "content": "我看光盤學會了幾個姿勢，你能不能陪我複習一下 ",
      "length": 23,
      "addedAt": "2026-05-20T20:56:05.380Z"
    },
    {
      "id": 45,
      "content": "土豆和馬鈴薯 番茄和西紅柿 小仙女和我",
      "length": 19,
      "addedAt": "2026-05-20T20:56:05.380Z"
    },
    {
      "id": 46,
      "content": "你那麼傻，沒我怎麼辦 ",
      "length": 11,
      "addedAt": "2026-05-20T20:56:05.380Z"
    },
    {
      "id": 47,
      "content": "精神上都這麼喜歡你了，如果不想睡你的話，感覺對你的肉體特別不尊敬 ",
      "length": 33,
      "addedAt": "2026-05-20T20:56:05.380Z"
    },
    {
      "id": 48,
      "content": "我：想吃我媽做的東西嗎？ 他：什麼？ 我：我。",
      "length": 23,
      "addedAt": "2026-05-20T20:56:05.380Z"
    },
    {
      "id": 49,
      "content": "在這個冬天遇到你 也許是最溫暖的吧 ",
      "length": 18,
      "addedAt": "2026-05-20T20:56:05.380Z"
    },
    {
      "id": 50,
      "content": "無論在哪裡遇到你 我都會喜歡上你",
      "length": 16,
      "addedAt": "2026-05-20T20:56:05.380Z"
    }
  ]
}