{
  "type": "騷話文案",
  "updated": "2026-02-12T12:27:11.609Z",
  "updateTime": "2026/2/12 下午8:27:11",
  "totalCount": 50,
  "targetCount": 50,
  "completionRate": "100.0%",
  "convertedToTraditional": true,
  "copywritings": [
    {
      "id": 1,
      "content": "想要嗎？求我啊 ",
      "length": 8,
      "addedAt": "2026-02-12T12:27:11.609Z"
    },
    {
      "id": 2,
      "content": "女人，就像馬路一樣，越是凹凸不平，越是危險",
      "length": 21,
      "addedAt": "2026-02-12T12:27:11.609Z"
    },
    {
      "id": 3,
      "content": "I really miss you. I wish we were together right now.",
      "length": 53,
      "addedAt": "2026-02-12T12:27:11.609Z"
    },
    {
      "id": 4,
      "content": "不要在該放蕩的年齡端莊的活著",
      "length": 14,
      "addedAt": "2026-02-12T12:27:11.609Z"
    },
    {
      "id": 5,
      "content": "你能來一下嗎?我家..燈壞了。",
      "length": 15,
      "addedAt": "2026-02-12T12:27:11.609Z"
    },
    {
      "id": 6,
      "content": "夢裡夢見的人，醒來就該去睡了他。 ",
      "length": 17,
      "addedAt": "2026-02-12T12:27:11.609Z"
    },
    {
      "id": 7,
      "content": "出來吧，平胸怪獸",
      "length": 8,
      "addedAt": "2026-02-12T12:27:11.609Z"
    },
    {
      "id": 8,
      "content": "過什麼兒童節，叔叔讓你明年過母親節 ",
      "length": 18,
      "addedAt": "2026-02-12T12:27:11.609Z"
    },
    {
      "id": 9,
      "content": "男生洗澡5分鐘，而女生要半小時。那麼問題來了，如果男女一起洗要多久呢？ ",
      "length": 36,
      "addedAt": "2026-02-12T12:27:11.609Z"
    },
    {
      "id": 10,
      "content": "我想要的很簡單，時光還在，你還在。 ",
      "length": 18,
      "addedAt": "2026-02-12T12:27:11.609Z"
    },
    {
      "id": 11,
      "content": "你一百種樣子 我一百種喜歡",
      "length": 13,
      "addedAt": "2026-02-12T12:27:11.609Z"
    },
    {
      "id": 12,
      "content": "姑娘，你就跟我敞開胸膛說亮話吧，我保證認真看你講話。",
      "length": 26,
      "addedAt": "2026-02-12T12:27:11.609Z"
    },
    {
      "id": 13,
      "content": "大吃億精",
      "length": 4,
      "addedAt": "2026-02-12T12:27:11.609Z"
    },
    {
      "id": 14,
      "content": "晚上吃茄子還是吃苦瓜",
      "length": 10,
      "addedAt": "2026-02-12T12:27:11.609Z"
    },
    {
      "id": 15,
      "content": "有些男生和女生說話時完全沒技巧，和兄弟調起情來卻一套一套的 ",
      "length": 30,
      "addedAt": "2026-02-12T12:27:11.609Z"
    },
    {
      "id": 16,
      "content": "情侶之間玩套路 也要把握好分寸 ",
      "length": 16,
      "addedAt": "2026-02-12T12:27:11.609Z"
    },
    {
      "id": 17,
      "content": "趙兄，託你幫我辦點事！啥事？這件事嘛，就是你倒過來讀這句話",
      "length": 29,
      "addedAt": "2026-02-12T12:27:11.609Z"
    },
    {
      "id": 18,
      "content": "對於那些滿嘴汙話的人 不要輕易的以為他們只是汙著玩玩，其實他們是認真的。",
      "length": 36,
      "addedAt": "2026-02-12T12:27:11.609Z"
    },
    {
      "id": 19,
      "content": "相遇總有原因，不是恩賜，就是教訓",
      "length": 16,
      "addedAt": "2026-02-12T12:27:11.609Z"
    },
    {
      "id": 20,
      "content": "遇見你之前我一直以為自己是百般挑剔的人，遇見你之後我才發現只要和你在一起就足夠幸福 ",
      "length": 42,
      "addedAt": "2026-02-12T12:27:11.609Z"
    },
    {
      "id": 21,
      "content": "姐最強大的事情，就是不靠菸酒，也能流氓並文藝著。 ",
      "length": 25,
      "addedAt": "2026-02-12T12:27:11.609Z"
    },
    {
      "id": 22,
      "content": "我和她不是青梅竹馬 卻被一手從小玩到大 ",
      "length": 20,
      "addedAt": "2026-02-12T12:27:11.609Z"
    },
    {
      "id": 23,
      "content": "夾道歡迎 ",
      "length": 5,
      "addedAt": "2026-02-12T12:27:11.609Z"
    },
    {
      "id": 24,
      "content": "“我最近覺得胸悶” “為什麼” “因為你卡在我的心裡” ",
      "length": 28,
      "addedAt": "2026-02-12T12:27:11.609Z"
    },
    {
      "id": 25,
      "content": "腳冷了吧？手冷了吧？ 過來！把手腳伸到我懷裡 ",
      "length": 23,
      "addedAt": "2026-02-12T12:27:11.609Z"
    },
    {
      "id": 26,
      "content": "我就是你的乾燥劑，等你溼了就幹你 ",
      "length": 17,
      "addedAt": "2026-02-12T12:27:11.609Z"
    },
    {
      "id": 27,
      "content": "我見過最美的畫面，便是你我汗如雨下。 ",
      "length": 19,
      "addedAt": "2026-02-12T12:27:11.609Z"
    },
    {
      "id": 28,
      "content": "人只要還活著，就肯定會遇到喜歡的人。。。。。。和她對象在一起。 ",
      "length": 32,
      "addedAt": "2026-02-12T12:27:11.609Z"
    },
    {
      "id": 29,
      "content": "妹妹都被草得脹痛了 還想再來一發 ",
      "length": 17,
      "addedAt": "2026-02-12T12:27:11.609Z"
    },
    {
      "id": 30,
      "content": "你對我冷淡的時候我真的想給你灌春藥 ",
      "length": 18,
      "addedAt": "2026-02-12T12:27:11.609Z"
    },
    {
      "id": 31,
      "content": "我愛你 沒有技巧 真誠野蠻",
      "length": 13,
      "addedAt": "2026-02-12T12:27:11.609Z"
    },
    {
      "id": 32,
      "content": "我喜歡她吞吞吐吐，可她喜歡我一臉懵逼",
      "length": 18,
      "addedAt": "2026-02-12T12:27:11.609Z"
    },
    {
      "id": 33,
      "content": "美好的事情記得一兩件，就足以釀酒了。",
      "length": 18,
      "addedAt": "2026-02-12T12:27:11.609Z"
    },
    {
      "id": 34,
      "content": "幼兒園小芳老師指著黑板上m、a、y、d、b幾個拼音考小朋友，小朋友們用最標準的發 音說：“摸-阿-姨-的-波。。。”",
      "length": 58,
      "addedAt": "2026-02-12T12:27:11.609Z"
    },
    {
      "id": 35,
      "content": "你說什麼 我都愛你 ",
      "length": 10,
      "addedAt": "2026-02-12T12:27:11.609Z"
    },
    {
      "id": 36,
      "content": "知乎日報-每天3次,每次7分鐘",
      "length": 15,
      "addedAt": "2026-02-12T12:27:11.609Z"
    },
    {
      "id": 37,
      "content": "我所有的體液 都有想你的味道",
      "length": 14,
      "addedAt": "2026-02-12T12:27:11.609Z"
    },
    {
      "id": 38,
      "content": "喘的這麼厲害！你在幹什麼？ ",
      "length": 14,
      "addedAt": "2026-02-12T12:27:11.609Z"
    },
    {
      "id": 39,
      "content": "我很孤獨用英文怎麼說。 “i love you”",
      "length": 24,
      "addedAt": "2026-02-12T12:27:11.609Z"
    },
    {
      "id": 40,
      "content": "上天算什麼 有本事上我 ",
      "length": 12,
      "addedAt": "2026-02-12T12:27:11.609Z"
    },
    {
      "id": 41,
      "content": "皂滑弄人 ",
      "length": 5,
      "addedAt": "2026-02-12T12:27:11.609Z"
    },
    {
      "id": 42,
      "content": "別灰心 人生不就是這樣嗎 起起落落落落落落落落落落落落的 ",
      "length": 29,
      "addedAt": "2026-02-12T12:27:11.609Z"
    },
    {
      "id": 43,
      "content": "“為什麼我的臉這麼長肩那麼寬？” “因為你是被你父母拉扯大的”",
      "length": 31,
      "addedAt": "2026-02-12T12:27:11.609Z"
    },
    {
      "id": 44,
      "content": "不管你以後遇到多少人 她們都是酒店而我是家 ",
      "length": 22,
      "addedAt": "2026-02-12T12:27:11.609Z"
    },
    {
      "id": 45,
      "content": "我都捨不得欺負的人 哪能讓別人欺負？ ",
      "length": 19,
      "addedAt": "2026-02-12T12:27:11.609Z"
    },
    {
      "id": 46,
      "content": "二十更更，三十夜夜，四十月月 ",
      "length": 15,
      "addedAt": "2026-02-12T12:27:11.609Z"
    },
    {
      "id": 47,
      "content": "種什麼花啊，我們一起種草莓 ",
      "length": 14,
      "addedAt": "2026-02-12T12:27:11.609Z"
    },
    {
      "id": 48,
      "content": "要不是看你奶子大 我早打你了 ",
      "length": 15,
      "addedAt": "2026-02-12T12:27:11.609Z"
    },
    {
      "id": 49,
      "content": "你好厲害 ",
      "length": 5,
      "addedAt": "2026-02-12T12:27:11.609Z"
    },
    {
      "id": 50,
      "content": "“你好。” “你比我更好。”",
      "length": 14,
      "addedAt": "2026-02-12T12:27:11.609Z"
    }
  ]
}