{
  "type": "騷話文案",
  "updated": "2025-11-29T01:16:40.148Z",
  "updateTime": "2025/11/29 上午9:16:40",
  "totalCount": 50,
  "targetCount": 50,
  "completionRate": "100.0%",
  "convertedToTraditional": true,
  "copywritings": [
    {
      "id": 1,
      "content": "“總說我嘴硬，你不吻一下怎麼知道是不是軟的？” ",
      "length": 24,
      "addedAt": "2025-11-29T01:16:40.148Z"
    },
    {
      "id": 2,
      "content": "我的一生（身），是我能夠給你的最好禮物。",
      "length": 20,
      "addedAt": "2025-11-29T01:16:40.148Z"
    },
    {
      "id": 3,
      "content": "“下雪了你為什麼不帶帽子？” “因為啊，想和你一路白頭啊～” ",
      "length": 31,
      "addedAt": "2025-11-29T01:16:40.148Z"
    },
    {
      "id": 4,
      "content": "“做個賊，早晨偷走你的棉被，夜晚偷走你的熱吻。”  ",
      "length": 26,
      "addedAt": "2025-11-29T01:16:40.148Z"
    },
    {
      "id": 5,
      "content": "浪蕩一生 鍾情一人 微風十里 只想要你。",
      "length": 20,
      "addedAt": "2025-11-29T01:16:40.148Z"
    },
    {
      "id": 6,
      "content": "我是玩球玩的最好的男人 ",
      "length": 12,
      "addedAt": "2025-11-29T01:16:40.148Z"
    },
    {
      "id": 7,
      "content": "喝最烈的酒，操最愛的人 ",
      "length": 12,
      "addedAt": "2025-11-29T01:16:40.148Z"
    },
    {
      "id": 8,
      "content": "我看你挺會吃的 吃我好不好 ",
      "length": 14,
      "addedAt": "2025-11-29T01:16:40.148Z"
    },
    {
      "id": 9,
      "content": "我發現你是個照騙 因為本人比照片好看多了",
      "length": 20,
      "addedAt": "2025-11-29T01:16:40.148Z"
    },
    {
      "id": 10,
      "content": "走路要牽著我呀，小時候老師沒有跟你說過貴重物品要隨身攜帶嗎！ ",
      "length": 31,
      "addedAt": "2025-11-29T01:16:40.148Z"
    },
    {
      "id": 11,
      "content": "三生有幸遇見你 縱使無緣亦不悔 ",
      "length": 16,
      "addedAt": "2025-11-29T01:16:40.148Z"
    },
    {
      "id": 12,
      "content": "親愛的，我想喝豆漿了！ ",
      "length": 12,
      "addedAt": "2025-11-29T01:16:40.148Z"
    },
    {
      "id": 13,
      "content": "我有個秘密需要嘴對嘴告訴你",
      "length": 13,
      "addedAt": "2025-11-29T01:16:40.148Z"
    },
    {
      "id": 14,
      "content": "老公，我要吃烤腸! ",
      "length": 10,
      "addedAt": "2025-11-29T01:16:40.148Z"
    },
    {
      "id": 15,
      "content": "我想和你 每天做四件事 一日三餐 ",
      "length": 17,
      "addedAt": "2025-11-29T01:16:40.148Z"
    },
    {
      "id": 16,
      "content": "你還是走吧，就當沒有我這個小炮友。",
      "length": 17,
      "addedAt": "2025-11-29T01:16:40.148Z"
    },
    {
      "id": 17,
      "content": "I need you pleaseeeeeeeeee ",
      "length": 27,
      "addedAt": "2025-11-29T01:16:40.148Z"
    },
    {
      "id": 18,
      "content": "你怎麼這麼矮” “因為我一直迷你啊” ",
      "length": 19,
      "addedAt": "2025-11-29T01:16:40.148Z"
    },
    {
      "id": 19,
      "content": "花前月下，不如花錢日下。 ",
      "length": 13,
      "addedAt": "2025-11-29T01:16:40.148Z"
    },
    {
      "id": 20,
      "content": "你的名字比嗯嗯嗯啊啊啊還動聽",
      "length": 14,
      "addedAt": "2025-11-29T01:16:40.148Z"
    },
    {
      "id": 21,
      "content": "好久都沒有日了 連續幾天陰天",
      "length": 14,
      "addedAt": "2025-11-29T01:16:40.148Z"
    },
    {
      "id": 22,
      "content": "晚安，來睡我吧 ",
      "length": 8,
      "addedAt": "2025-11-29T01:16:40.148Z"
    },
    {
      "id": 23,
      "content": "別等不該等的人，別傷不該傷的心，我們都是為了性生活 ",
      "length": 26,
      "addedAt": "2025-11-29T01:16:40.148Z"
    },
    {
      "id": 24,
      "content": "我沒有想要和你對著幹……我想要後入",
      "length": 17,
      "addedAt": "2025-11-29T01:16:40.148Z"
    },
    {
      "id": 25,
      "content": "感情是可以慢慢培養的，實在培養不了的話，可以試試在床上調教。",
      "length": 30,
      "addedAt": "2025-11-29T01:16:40.148Z"
    },
    {
      "id": 26,
      "content": "在和女朋友確定戀愛關係之前，帶她去吃一次海鮮，如果這個女生很怕腥味，沒關係，以後告訴她你的是檸檬味的 ",
      "length": 51,
      "addedAt": "2025-11-29T01:16:40.148Z"
    },
    {
      "id": 27,
      "content": "今夜讓你在床上發狂 ",
      "length": 10,
      "addedAt": "2025-11-29T01:16:40.148Z"
    },
    {
      "id": 28,
      "content": "別被我的魅力迷倒了，你要看我的床技，口技",
      "length": 20,
      "addedAt": "2025-11-29T01:16:40.148Z"
    },
    {
      "id": 29,
      "content": "想去有你的城市流浪，去你住的地方逛逛. ",
      "length": 20,
      "addedAt": "2025-11-29T01:16:40.148Z"
    },
    {
      "id": 30,
      "content": "曾經硬著等 現在等著硬 ",
      "length": 12,
      "addedAt": "2025-11-29T01:16:40.148Z"
    },
    {
      "id": 31,
      "content": "老子撲過來就是一個啪啪啪 ",
      "length": 13,
      "addedAt": "2025-11-29T01:16:40.148Z"
    },
    {
      "id": 32,
      "content": "太晚了宿舍要關門了",
      "length": 9,
      "addedAt": "2025-11-29T01:16:40.148Z"
    },
    {
      "id": 33,
      "content": "你猜我喜歡什麼制服，被你制服",
      "length": 14,
      "addedAt": "2025-11-29T01:16:40.148Z"
    },
    {
      "id": 34,
      "content": "你吃了什麼春藥，這麼騷 ",
      "length": 12,
      "addedAt": "2025-11-29T01:16:40.148Z"
    },
    {
      "id": 35,
      "content": "要試試我草莓味的唇膏嗎？",
      "length": 12,
      "addedAt": "2025-11-29T01:16:40.148Z"
    },
    {
      "id": 36,
      "content": "我是有多愛你 幹誰眼裡都是你 ",
      "length": 15,
      "addedAt": "2025-11-29T01:16:40.148Z"
    },
    {
      "id": 37,
      "content": "我感覺我倆今生是可以睡在一張床上的人  ",
      "length": 20,
      "addedAt": "2025-11-29T01:16:40.148Z"
    },
    {
      "id": 38,
      "content": "十一在家閒著沒事 幫忙照顧18到28cm的男孩子 ",
      "length": 25,
      "addedAt": "2025-11-29T01:16:40.148Z"
    },
    {
      "id": 39,
      "content": "雖然我想和你睡在一起確實是想摸摸你佔你便宜。",
      "length": 22,
      "addedAt": "2025-11-29T01:16:40.148Z"
    },
    {
      "id": 40,
      "content": "弱水三千，我只嫖你一個 ",
      "length": 12,
      "addedAt": "2025-11-29T01:16:40.148Z"
    },
    {
      "id": 41,
      "content": "寶寶,乖乖坐上來 ",
      "length": 9,
      "addedAt": "2025-11-29T01:16:40.148Z"
    },
    {
      "id": 42,
      "content": "在我左腿右邊，右腿的左邊有一隻小精靈，它活潑又聰明 ",
      "length": 26,
      "addedAt": "2025-11-29T01:16:40.148Z"
    },
    {
      "id": 43,
      "content": "看著你開心我就開心",
      "length": 9,
      "addedAt": "2025-11-29T01:16:40.148Z"
    },
    {
      "id": 44,
      "content": "The way you hold me is so hot ",
      "length": 30,
      "addedAt": "2025-11-29T01:16:40.148Z"
    },
    {
      "id": 45,
      "content": "穿上裙子跟我去小樹林做做",
      "length": 12,
      "addedAt": "2025-11-29T01:16:40.148Z"
    },
    {
      "id": 46,
      "content": "不要讓我看見你 不然看見一次幹一次",
      "length": 17,
      "addedAt": "2025-11-29T01:16:40.148Z"
    },
    {
      "id": 47,
      "content": "I want U.Right.Now. ",
      "length": 20,
      "addedAt": "2025-11-29T01:16:40.148Z"
    },
    {
      "id": 48,
      "content": "“我可以走在你後面嗎？” “為什麼？” “因為我想做你背後的女人” ",
      "length": 34,
      "addedAt": "2025-11-29T01:16:40.148Z"
    },
    {
      "id": 49,
      "content": "分不清寵愛和佔有，只是想在睡前與你纏綿，深深吻你，睡夢中也緊抱著你 ",
      "length": 34,
      "addedAt": "2025-11-29T01:16:40.148Z"
    },
    {
      "id": 50,
      "content": "你總是磨磨蹭蹭，我總是吞吞吐吐",
      "length": 15,
      "addedAt": "2025-11-29T01:16:40.148Z"
    }
  ]
}